{
    "key": "group_6373dbf50ec8f",
    "title": "Shocklogic banner",
    "fields": [
        {
            "key": "field_6373dbf5933ff",
            "label": "Shocklogic banner group",
            "name": "shocklogic_banner_group",
            "aria-label": "",
            "type": "group",
            "instructions": "",
            "required": 0,
            "conditional_logic": 0,
            "wrapper": {
                "width": "",
                "class": "",
                "id": ""
            },
            "layout": "block",
            "acfe_seamless_style": 1,
            "sub_fields": [
                {
                    "key": "field_6373dc9d93400",
                    "label": "image",
                    "name": "image",
                    "aria-label": "",
                    "type": "image",
                    "instructions": "",
                    "required": 0,
                    "conditional_logic": 0,
                    "wrapper": {
                        "width": "",
                        "class": "",
                        "id": ""
                    },
                    "uploader": "",
                    "acfe_thumbnail": 0,
                    "return_format": "array",
                    "min_width": "",
                    "min_height": "",
                    "min_size": "",
                    "max_width": "",
                    "max_height": "",
                    "max_size": "",
                    "mime_types": "",
                    "preview_size": "medium",
                    "library": "all"
                }
            ],
            "acfe_group_modal": 0,
            "acfe_group_modal_close": 0,
            "acfe_group_modal_button": "",
            "acfe_group_modal_size": "large"
        }
    ],
    "location": [
        [
            {
                "param": "block",
                "operator": "==",
                "value": "acf\/shocklogic-banner"
            }
        ]
    ],
    "menu_order": 0,
    "position": "normal",
    "style": "default",
    "label_placement": "left",
    "instruction_placement": "label",
    "hide_on_screen": "",
    "active": true,
    "description": "",
    "show_in_rest": 0,
    "acfe_display_title": "",
    "acfe_autosync": [
        "php",
        "json"
    ],
    "acfe_form": 0,
    "acfe_meta": "",
    "acfe_note": "",
    "modified": 1668538846
}